fi/__init__.py
fi/opt/__init__.py
fi/opt/types.py
fi/opt/base/__init__.py
fi/opt/base/base_generator.py
fi/opt/base/base_mapper.py
fi/opt/base/base_optimizer.py
fi/opt/base/evaluator.py
fi/opt/datamappers/__init__.py
fi/opt/datamappers/basic_mapper.py
fi/opt/generators/__init__.py
fi/opt/generators/litellm.py
fi/opt/optimizers/__init__.py
fi/opt/optimizers/bayesian_search.py
fi/opt/optimizers/gepa.py
fi/opt/optimizers/metaprompt.py
fi/opt/optimizers/promptwizard.py
fi/opt/optimizers/protegi.py
fi/opt/optimizers/random_search.py
fi/opt/utils/__init__.py
fi/opt/utils/setup_logging.py
agent_opt-0.0.1.dist-info/METADATA
agent_opt-0.0.1.dist-info/WHEEL
agent_opt-0.0.1.dist-info/top_level.txt
agent_opt-0.0.1.dist-info/RECORD
